concepttordf/__init__.py
concepttordf/alternativformulering.py
concepttordf/associativerelation.py
concepttordf/betydningsbeskrivelse.py
concepttordf/collection.py
concepttordf/concept.py
concepttordf/conceptrelation.py
concepttordf/contact.py
concepttordf/definition.py
concepttordf/genericrelation.py
concepttordf/partitiverelation.py
concepttordf-3.0.0.dist-info/LICENSE
concepttordf-3.0.0.dist-info/METADATA
concepttordf-3.0.0.dist-info/WHEEL
concepttordf-3.0.0.dist-info/RECORD
