Metadata-Version: 2.1
Name: concepttordf
Version: 3.0.0
Summary: A library for mapping a concept collection to rdf
Home-page: https://github.com/Informasjonsforvaltning/concepttordf
License: Apache-2.0
Author: Stig B. Dørmænen
Author-email: stigbd@gmail.com
Requires-Python: >=3.10,<3.13
Classifier: License :: OSI Approved :: Apache Software License
Classifier: Operating System :: OS Independent
Classifier: Programming Language :: Python :: 3
Classifier: Programming Language :: Python :: 3.10
Classifier: Programming Language :: Python :: 3.11
Classifier: Programming Language :: Python :: 3.12
Requires-Dist: rdflib (>=7.2.1,<8.0.0)
Requires-Dist: setuptools (>=80.0.0,<81.0.0)
Project-URL: Documentation, https://concepttordf.readthedocs.io
Project-URL: Repository, https://github.com/Informasjonsforvaltning/concepttordf
